hearthstone/__init__.py
hearthstone/bountyxml.py
hearthstone/cardxml.py
hearthstone/dbf.py
hearthstone/deckstrings.py
hearthstone/entities.py
hearthstone/enums.py
hearthstone/mercenaryxml.py
hearthstone/stringsfile.py
hearthstone/types.py
hearthstone/xmlutils.py
hearthstone/utils/__init__.py
hearthstone-9.19.6.dist-info/licenses/LICENSE
hearthstone-9.19.6.dist-info/METADATA
hearthstone-9.19.6.dist-info/WHEEL
hearthstone-9.19.6.dist-info/top_level.txt
hearthstone-9.19.6.dist-info/zip-safe
hearthstone-9.19.6.dist-info/RECORD
