Metadata-Version: 2.4
Name: hearthstone
Version: 9.19.6
Summary: CardDefs.xml parser and Hearthstone enums for Python
Home-page: https://github.com/HearthSim/python-hearthstone/
Download-URL: https://github.com/HearthSim/python-hearthstone/tarball/master
Author: Jerome Leclanche
Author-email: jerome@leclan.ch
Classifier: Development Status :: 5 - Production/Stable
Classifier: Intended Audience :: Developers
Classifier: License :: OSI Approved :: MIT License
Classifier: Programming Language :: Python
Classifier: Programming Language :: Python :: 3
Classifier: Programming Language :: Python :: 3.6
Classifier: Topic :: Games/Entertainment
Requires-Python: >=3.6
License-File: LICENSE
Requires-Dist: requests
Dynamic: download-url
Dynamic: license-file
